cmdlm/__init__.py
cmdlm/chat/__init__.py
cmdlm/chat/compact_handler.py
cmdlm/chat/console.py
cmdlm/chat/control.py
cmdlm/chat/persistence.py
cmdlm/chat/prompt_manager.py
cmdlm/chat/session.py
cmdlm/cli/__init__.py
cmdlm/cli/__main__.py
cmdlm/cli/main.py
cmdlm/cli/setup.py
cmdlm/commands/__init__.py
cmdlm/commands/custom_date_command.py
cmdlm/commands/file_command.py
cmdlm/commands/folder_command.py
cmdlm/commands/github_command.py
cmdlm/commands/image_command.py
cmdlm/commands/manager.py
cmdlm/commands/pdf_command.py
cmdlm/commands/processor.py
cmdlm/commands/registry.py
cmdlm/commands/shell_command.py
cmdlm/config/__init__.py
cmdlm/config/manager.py
cmdlm/config/providers.py
cmdlm/conversation/__init__.py
cmdlm/conversation/handler.py
cmdlm/prompts/compact.txt
cmdlm/tools/__init__.py
cmdlm/tools/base.py
cmdlm/tools/manager.py
cmdlm/tools/registry.py
cmdlm/utils/prompts.py
cmdlm/utils/readline_compatibility.py
cmdlm-0.0.2.dist-info/METADATA
cmdlm-0.0.2.dist-info/WHEEL
cmdlm-0.0.2.dist-info/entry_points.txt
cmdlm-0.0.2.dist-info/licenses/LICENSE
cmdlm-0.0.2.dist-info/RECORD
