Metadata-Version: 2.4
Name: cmdlm
Version: 0.0.2
Summary: Simple CLI tool to command and use langauge models from the command line
Author-email: AI-4-ALL <ai4all2505@gmail.com>
License-File: LICENSE
Requires-Python: >=3.10
Requires-Dist: aiofiles>=24.1.0
Requires-Dist: aiohttp>=3.12.15
Requires-Dist: click>=8.2.1
Requires-Dist: cryptography>=45.0.5
Requires-Dist: gitingest>=0.3.0
Requires-Dist: gnureadline<9.0.0,>=8.2.13; sys_platform != 'win32'
Requires-Dist: litellm>=1.64.1
Requires-Dist: prompt-toolkit>=3.0.51
Requires-Dist: pyperclip>=1.9.0
Requires-Dist: pyreadline3<4.0.0,>=3.4.1; sys_platform == 'win32'
Requires-Dist: requests>=2.32.4
Requires-Dist: rich>=14.1.0
